slipway/__init__.py
slipway/binds.py
slipway/client/__init__.py
slipway/client/docker.py
slipway/client/podman.py
slipway/configuration.py
slipway/container.py
slipway/image.py
slipway/util.py
slipway/volumes.py
slipway/xdg_open/__init__.py
slipway/xdg_open/client.py
slipway/xdg_open/server.py
slipway-0.14.0.dist-info/entry_points.txt
slipway-0.14.0.dist-info/LICENSE
slipway-0.14.0.dist-info/WHEEL
slipway-0.14.0.dist-info/METADATA
slipway-0.14.0.dist-info/RECORD
